topotest/__init__.py
topotest/distributions.py
topotest/ecc.py
topotest/topotest.py
topotest-0.1.0.dist-info/LICENCE.md
topotest-0.1.0.dist-info/METADATA
topotest-0.1.0.dist-info/WHEEL
topotest-0.1.0.dist-info/top_level.txt
topotest-0.1.0.dist-info/RECORD
