Metadata-Version: 2.1
Name: topotest
Version: 0.1.0
Summary: Onesample and twosample topological goodness-of-fit tests
Author: Rafal Topolnicki
License-File: LICENCE.md
Requires-Dist: numpy
Requires-Dist: gudhi
Requires-Dist: scikit-learn
Requires-Dist: pandas
Requires-Dist: tqdm
